ghsa_client/__init__.py
ghsa_client/client.py
ghsa_client/py.typed
ghsa_client/exceptions/__init__.py
ghsa_client/exceptions/cvss.py
ghsa_client/exceptions/rate_limit.py
ghsa_client/models/__init__.py
ghsa_client/models/advisory.py
ghsa_client/models/cve_id.py
ghsa_client/models/cvss.py
ghsa_client/models/ecosystem.py
ghsa_client/models/ghsa_id.py
ghsa_client/models/language.py
ghsa_client/models/package.py
ghsa_client/models/version.py
ghsa_client/models/vulnerability.py
ghsa_client-1.5.0.dist-info/METADATA
ghsa_client-1.5.0.dist-info/WHEEL
ghsa_client-1.5.0.dist-info/licenses/LICENSE
ghsa_client-1.5.0.dist-info/RECORD
